{
  "designerVersion": 1,
  "id": "081cd8ec88d84fa2bfc39bac56c9144c",
  "allowMetrics": true,
  "helperText": "",
  "name": "cart-upsell-sidebar",
  "strictPrivateRead": false,
  "allowBuiltInComponents": true,
  "allowHeatmap": true,
  "archived": false,
  "webhooks": [],
  "componentsOnlyMode": false,
  "showAbTests": true,
  "autoTracked": true,
  "createdDate": 1631307261211,
  "sendToMongoDb": true,
  "showTargeting": true,
  "defaultQuery": [],
  "injectWcAt": "",
  "strictPrivateWrite": false,
  "useQueryParamTargetingClientSide": false,
  "injectWcPosition": "",
  "publicReadable": true,
  "apiGenerated": true,
  "requiredTargets": [],
  "bigData": false,
  "showMetrics": true,
  "lastUpdateBy": null,
  "pathPrefix": "/",
  "examplePageUrl": "",
  "allowTests": true,
  "getSchemaFromPage": false,
  "hideOptions": false,
  "hooks": {},
  "individualEmbed": false,
  "hideFromUI": false,
  "publicWritable": false,
  "kind": "component",
  "repeatable": false,
  "showScheduling": true,
  "@originId": "953b09d275bbb145858565ee9a39294d35903d1b556451d6776655956d6df47c",
  "hidden": false,
  "isPage": false,
  "sendToElasticSearch": false,
  "schema": {},
  "subType": "",
  "fields": [
    {
      "noPhotoPicker": false,
      "showIf": "",
      "required": true,
      "@type": "@builder.io/core:Field",
      "mandatory": false,
      "onChange": "",
      "permissionsRequiredToEdit": "",
      "simpleTextOnly": false,
      "disallowRemove": false,
      "subFields": [],
      "showTemplatePicker": true,
      "hideFromUI": false,
      "copyOnAdd": true,
      "model": "",
      "advanced": false,
      "hidden": false,
      "type": "uiBlocks",
      "helperText": "",
      "hideFromFieldsEditor": true,
      "autoFocus": false,
      "name": "blocks"
    }
  ],
  "singleton": false
}
